ae_mitiq/__init__.py
ae_mitiq/autoencoder.tflite
ae_mitiq/core.py
ae_mitiq/mitigation.py
ae_mitiq/models.py
ae_mitiq/plot_utils.py
ae_mitiq/utils.py
ae_mitiq-0.0.4.dist-info/METADATA
ae_mitiq-0.0.4.dist-info/WHEEL
ae_mitiq-0.0.4.dist-info/top_level.txt
ae_mitiq-0.0.4.dist-info/RECORD
