Metadata-Version: 2.4
Name: ae-mitiq
Version: 0.0.4
Summary: Quantum error mitigation with pretrained autoencoder model.
Author-email: LIN XIAO DAO <112755009@g.nccu.edu.tw>
Requires-Dist: numpy
Requires-Dist: qiskit<2.0,>=1.2
Requires-Dist: qiskit_ibm_runtime>0.3
Requires-Dist: qiskit_aer
Requires-Dist: matplotlib
Requires-Dist: pylatexenc
Requires-Dist: ai_edge_litert
Requires-Dist: dash
Requires-Dist: plotly
